FileHandler.py
__init__.py
examples.py
language_pack.py
print_replace.py
documentation/source/conf.py
scripts/localizer_pack_fill.py
scripts/update_version.py
supported_file_types/__init__.py
supported_file_types/dot_csv.py
supported_file_types/dot_json.py
perfect_localizer-1.4.dist-info/METADATA
perfect_localizer-1.4.dist-info/WHEEL
perfect_localizer-1.4.dist-info/entry_points.txt
perfect_localizer-1.4.dist-info/licenses/LICENSE
perfect_localizer-1.4.dist-info/RECORD
